mmdb_writer.py
mmdb_writer-0.1.1.dist-info/LICENSE
mmdb_writer-0.1.1.dist-info/WHEEL
mmdb_writer-0.1.1.dist-info/METADATA
mmdb_writer-0.1.1.dist-info/RECORD
