Metadata-Version: 2.1
Name: mmdb-writer
Version: 0.1.1
Summary: Make mmdb format ip library file which can be read by maxmind official language reader
Home-page: https://github.com/vimt/MaxMind-DB-Writer-python
License: MIT
Author: VimT
Requires-Python: >=3.7,<4.0
Classifier: License :: OSI Approved :: MIT License
Classifier: Programming Language :: Python :: 3
Classifier: Programming Language :: Python :: 3.7
Classifier: Programming Language :: Python :: 3.8
Classifier: Programming Language :: Python :: 3.9
Classifier: Programming Language :: Python :: 3.10
Classifier: Programming Language :: Python :: 3.11
Requires-Dist: maxminddb (>=2.0,<3.0)
Requires-Dist: netaddr (>=0.7.0,<1.0)
